flake8_pantsbuild.py
flake8_pantsbuild-2.0.0.dist-info/entry_points.txt
flake8_pantsbuild-2.0.0.dist-info/LICENSE
flake8_pantsbuild-2.0.0.dist-info/WHEEL
flake8_pantsbuild-2.0.0.dist-info/METADATA
flake8_pantsbuild-2.0.0.dist-info/RECORD
