Metadata-Version: 2.1
Name: flake8-pantsbuild
Version: 2.0.0
Summary: Various Flake8 lints used by the Pants project and its users.
Home-page: https://pants.readme.io/docs/python-linters-and-formatters
License: Apache-2.0
Author: Pantsbuild developers
Author-email: pantsbuild@gmail.com
Requires-Python: >=3.6
Classifier: Intended Audience :: Developers
Classifier: License :: OSI Approved :: Apache Software License
Classifier: Programming Language :: Python :: 3
Classifier: Programming Language :: Python :: 3.6
Classifier: Programming Language :: Python :: 3.7
Classifier: Programming Language :: Python :: 3.8
Classifier: Topic :: Software Development :: Build Tools
Requires-Dist: flake8 (>=3.7)
Requires-Dist: importlib_metadata (>=1.3.0); python_version < "3.8"
Project-URL: Repository, https://github.com/pantsbuild/flake8-pantsbuild
